NCBIGeneInfo/NCBI_gene_dict
NCBIGeneInfo/__init__.py
NCBIGeneInfo/gene_info.py
NCBIGeneInfo-0.1.dist-info/LICENSE.txt
NCBIGeneInfo-0.1.dist-info/METADATA
NCBIGeneInfo-0.1.dist-info/WHEEL
NCBIGeneInfo-0.1.dist-info/top_level.txt
NCBIGeneInfo-0.1.dist-info/RECORD
