Metadata-Version: 2.1
Name: NCBIGeneInfo
Version: 0.1
Summary: A package to retrieve gene information from NCBI
Home-page: https://github.com/sharifrahmanie/NCBIGeneInfo/archive/refs/tags/v0.1.tar.gz
Author: Edris Sharif Rahmani
Author-email: rahmani.biotech@gmail.com
License: MIT
Keywords: NCBI,Gene symbol,Gene,Bioinformatics
Platform: UNKNOWN
Classifier: Programming Language :: Python :: 3
Classifier: License :: OSI Approved :: MIT License
Classifier: Operating System :: OS Independent
License-File: LICENSE.txt
Requires-Dist: beautifulsoup4
Requires-Dist: requests
